langchain_ibm_watson/__init__.py
langchain_ibm_watson/document_loaders.py
langchain_ibm_watson/document_transformers.py
langchain_ibm_watson/retrievers.py
langchain_ibm_watson/storage.py
langchain_ibm_watson/tools.py
langchain_ibm_watson-0.0.1.dist-info/LICENSE
langchain_ibm_watson-0.0.1.dist-info/METADATA
langchain_ibm_watson-0.0.1.dist-info/WHEEL
langchain_ibm_watson-0.0.1.dist-info/RECORD
